MANIFEST.in
README.rst
requirements.txt
setup.cfg
setup.py
bin/tpq
tpq/__init__.py
tpq/__main__.py
tpq/sql.py
tpq/utils.py
tpq/version.py
tpq.egg-info/PKG-INFO
tpq.egg-info/SOURCES.txt
tpq.egg-info/dependency_links.txt
tpq.egg-info/not-zip-safe
tpq.egg-info/requires.txt
tpq.egg-info/top_level.txt