Metadata-Version: 1.1
Name: tpq
Version: 1.7
Summary: Trivial Postgres Queue
Home-page: https://github.com/btimby/tpq/
Author: Ben Timby
Author-email: btimby@smartfile.com
License: UNKNOWN
Platform: UNKNOWN
Classifier: Development Status :: 4 - Beta
Classifier: Environment :: Web Environment
Classifier: Intended Audience :: Developers
Classifier: Operating System :: OS Independent
Classifier: Programming Language :: Python
Classifier: Framework :: Django
